jupyterlab_graph_lsp/__init__.py
jupyterlab_graph_lsp/_version.py
jupyterlab_graph_lsp/install.json
jupyterlab_graph_lsp/labextension/package.json
jupyterlab_graph_lsp/labextension/static/310.55f9ae4dbc849e277851.js
jupyterlab_graph_lsp/labextension/static/568.7d6cf3eea9f318445c27.js
jupyterlab_graph_lsp/labextension/static/671.2d49df4f8965762f02b8.js
jupyterlab_graph_lsp/labextension/static/671.2e3b9c6b1f1b5a22f876.js
jupyterlab_graph_lsp/labextension/static/671.562d1e7e9335998ba9b2.js
jupyterlab_graph_lsp/labextension/static/671.a5ca4b1a62cbe328a3ee.js
jupyterlab_graph_lsp/labextension/static/671.bbac687a2f156aec303e.js
jupyterlab_graph_lsp/labextension/static/686.3bbb6ad0ef54dfae2cc2.js
jupyterlab_graph_lsp/labextension/static/686.6a6a8211ccc97144cf12.js
jupyterlab_graph_lsp/labextension/static/686.94b26e7664e4fe83693d.js
jupyterlab_graph_lsp/labextension/static/686.cece68898037933f0e62.js
jupyterlab_graph_lsp/labextension/static/686.e91cead405aa001c63e2.js
jupyterlab_graph_lsp/labextension/static/719.e8dcd5efe8c80f2c180f.js
jupyterlab_graph_lsp/labextension/static/remoteEntry.0f4c42b4bbc6e529a984.js
jupyterlab_graph_lsp/labextension/static/remoteEntry.17e47f8e1832cbe207d0.js
jupyterlab_graph_lsp/labextension/static/remoteEntry.19665cb59293a0e2a591.js
jupyterlab_graph_lsp/labextension/static/remoteEntry.1bc3e5067a5f21156937.js
jupyterlab_graph_lsp/labextension/static/remoteEntry.2fdbe3d91197194eae1d.js
jupyterlab_graph_lsp/labextension/static/remoteEntry.3834100f99d15c6a7207.js
jupyterlab_graph_lsp/labextension/static/remoteEntry.491e02f90dd344d85149.js
jupyterlab_graph_lsp/labextension/static/remoteEntry.5305c70c10c1a7cba8fc.js
jupyterlab_graph_lsp/labextension/static/remoteEntry.9ae95bd1feace03eb097.js
jupyterlab_graph_lsp/labextension/static/remoteEntry.f90a448577dd2cb10849.js
jupyterlab_graph_lsp/labextension/static/style.js
jupyterlab_graph_lsp/servers/__init__.py
jupyterlab_graph_lsp/servers/_base.py
jupyterlab_graph_lsp/servers/graphql.py
jupyterlab_graph_lsp-0.1.2.dist-info/LICENSE
jupyterlab_graph_lsp-0.1.2.dist-info/METADATA
jupyterlab_graph_lsp-0.1.2.dist-info/WHEEL
jupyterlab_graph_lsp-0.1.2.dist-info/entry_points.txt
jupyterlab_graph_lsp-0.1.2.dist-info/top_level.txt
jupyterlab_graph_lsp-0.1.2.dist-info/RECORD
