Metadata-Version: 2.1
Name: jupyterlab-graph-lsp
Version: 0.1.2
Summary: Graph Language Server extensions for jupyterlab-lsp
Home-page: UNKNOWN
Author: jupyterlab-graph-lsp Contributors
Author-email: freeman.dane@gmail.com
License: BSD-3-Clause
Project-URL: Bug Tracker, https://github.com/jupyrdf/jupyterlab-graph-lsp/issues
Project-URL: Source Code, https://github.com/jupyrdf/jupyterlab-graph-lsp
Keywords: Interactive,Language Server,LSP,Graphs
Platform: UNKNOWN
Classifier: Framework :: Jupyter
Classifier: Intended Audience :: Developers
Classifier: Intended Audience :: Information Technology
Classifier: License :: OSI Approved :: BSD License
Classifier: Programming Language :: Python
Requires-Python: >=3.6
License-File: LICENSE
Requires-Dist: jupyterlab-lsp (<4,>=3.5)
